tracardi_lang_detection/plugin.py
tracardi_lang_detection/model/configuration.py
tracardi_lang_detection/model/__pycache__/configuration.cpython-310.pyc
tracardi_lang_detection-0.1.dist-info/LICENSE.md
tracardi_lang_detection-0.1.dist-info/METADATA
tracardi_lang_detection-0.1.dist-info/WHEEL
tracardi_lang_detection-0.1.dist-info/top_level.txt
tracardi_lang_detection-0.1.dist-info/RECORD
